[
    {
        "id": "gba_Castlevania_-_Aria_of_Sorrow",
        "name": "Castlevania - Aria of Sorrow",
        "system": "gba",
        "rom_path": "roms/gba/Castlevania - Aria of Sorrow (USA).gba",
        "core": "mgba",
        "image": "assets/gba/Castlevania - Aria of Sorrow.png"
    },
    {
        "id": "gba_Dragon_Ball_-_Advanced_Adventure",
        "name": "Dragon Ball - Advanced Adventure",
        "system": "gba",
        "rom_path": "roms/gba/Dragon Ball - Advanced Adventure (USA).gba",
        "core": "mgba",
        "image": "assets/gba/Dragon Ball - Advanced Adventure.png"
    },
    {
        "id": "gba_F-Zero_-_Maximum_Velocity",
        "name": "F-Zero - Maximum Velocity",
        "system": "gba",
        "rom_path": "roms/gba/F-Zero - Maximum Velocity (UE) [!].gba",
        "core": "mgba",
        "image": "assets/gba/F-Zero - Maximum Velocity.png"
    },
    {
        "id": "gba_Final_Fantasy_Tactics_Advance",
        "name": "Final Fantasy Tactics Advance",
        "system": "gba",
        "rom_path": "roms/gba/Final Fantasy Tactics Advance (USA).gba",
        "core": "mgba",
        "image": "assets/gba/Final Fantasy Tactics Advance.png"
    },
    {
        "id": "gba_Final_Fantasy_VI_Advance",
        "name": "Final Fantasy VI Advance",
        "system": "gba",
        "rom_path": "roms/gba/Final Fantasy VI Advance (USA).gba",
        "core": "mgba",
        "image": "assets/gba/Final Fantasy VI Advance.png"
    },
    {
        "id": "gba_Fire_Emblem_-_The_Sacred_Stones",
        "name": "Fire Emblem - The Sacred Stones",
        "system": "gba",
        "rom_path": "roms/gba/Fire Emblem - The Sacred Stones (U).gba",
        "core": "mgba",
        "image": "assets/gba/Fire Emblem - The Sacred Stones.png"
    },
    {
        "id": "gba_Harvest_Moon_-_Friends_of_Mineral_Town",
        "name": "Harvest Moon - Friends of Mineral Town",
        "system": "gba",
        "rom_path": "roms/gba/Harvest Moon - Friends of Mineral Town (USA).gba",
        "core": "mgba",
        "image": "assets/gba/Harvest Moon - Friends of Mineral Town.png"
    },
    {
        "id": "gba_Mario_&_Luigi_-_Superstar_Saga",
        "name": "Mario & Luigi - Superstar Saga",
        "system": "gba",
        "rom_path": "roms/gba/Mario & Luigi - Superstar Saga (USA).gba",
        "core": "mgba",
        "image": "assets/gba/Mario  Luigi - Superstar Saga.png"
    },
    {
        "id": "gba_Mario_Kart_-_Super_Circuit",
        "name": "Mario Kart - Super Circuit",
        "system": "gba",
        "rom_path": "roms/gba/Mario Kart - Super Circuit (USA).gba",
        "core": "mgba",
        "image": "assets/gba/Mario Kart - Super Circuit.png"
    },
    {
        "id": "gba_Mega_Man_Zero",
        "name": "Mega Man Zero",
        "system": "gba",
        "rom_path": "roms/gba/Mega Man Zero (USA, Europe).gba",
        "core": "mgba",
        "image": "assets/gba/Mega Man Zero.png"
    },
    {
        "id": "gba_Metroid_Fusion",
        "name": "Metroid Fusion",
        "system": "gba",
        "rom_path": "roms/gba/Metroid Fusion (USA).gba",
        "core": "mgba",
        "image": "assets/gba/Metroid Fusion.png"
    },
    {
        "id": "gba_Mother_3",
        "name": "Mother 3",
        "system": "gba",
        "rom_path": "roms/gba/Mother 3.gba",
        "core": "mgba",
        "image": "assets/gba/Mother 3.png"
    },
    {
        "id": "gba_Pokemon_Emerald_Seaglass_3.0",
        "name": "Pokemon Emerald Seaglass 3.0",
        "system": "gba",
        "rom_path": "roms/gba/Pokemon Emerald Seaglass 3.0 (PokemonEmeraldseaglass.com).gba",
        "core": "mgba",
        "image": "assets/gba/Pokemon Emerald Seaglass 3.0.png"
    },
    {
        "id": "gba_Pokemon_Mystery_Dungeon_-_Red_Rescue_Team",
        "name": "Pokemon Mystery Dungeon - Red Rescue Team",
        "system": "gba",
        "rom_path": "roms/gba/Pokemon Mystery Dungeon - Red Rescue Team (USA, Australia).gba",
        "core": "mgba",
        "image": "assets/gba/Pokemon Mystery Dungeon - Red Rescue Team.png"
    },
    {
        "id": "gba_Super_Mario_Advance_3_-_Yoshi's_Island",
        "name": "Super Mario Advance 3 - Yoshi's Island",
        "system": "gba",
        "rom_path": "roms/gba/Super Mario Advance 3 - Yoshi's Island (USA).gba",
        "core": "mgba",
        "image": "assets/gba/Super Mario Advance 3 - Yoshis Island.png"
    },
    {
        "id": "gba_The_Legend_of_Zelda_-_The_Minish_Cap",
        "name": "The Legend of Zelda - The Minish Cap",
        "system": "gba",
        "rom_path": "roms/gba/The Legend of Zelda - The Minish Cap (USA).gba",
        "core": "mgba",
        "image": "https://raw.githubusercontent.com/libretro-thumbnails/Nintendo_-_Game_Boy_Advance/master/Named_Boxarts/Legend%20of%20Zelda%2C%20The%20-%20The%20Minish%20Cap%20%28USA%29.png"
    },
    {
        "id": "gba_Worms_-_World_Party",
        "name": "Worms - World Party",
        "system": "gba",
        "rom_path": "roms/gba/Worms - World Party (U) (M5).gba",
        "core": "mgba",
        "image": "assets/gba/Worms - World Party.png"
    },
    {
        "id": "gba_Yu-Gi-Oh!_-_Ultimate_Masters_-_World_Championship_Tournament_2006",
        "name": "Yu-Gi-Oh! - Ultimate Masters - World Championship Tournament 2006",
        "system": "gba",
        "rom_path": "roms/gba/Yu-Gi-Oh! - Ultimate Masters - World Championship Tournament 2006 (USA) (En,Ja,Fr,De,Es,It).gba",
        "core": "mgba",
        "image": "assets/gba/Yu-Gi-Oh - Ultimate Masters - World Championship Tournament 2006.png"
    },
    {
        "id": "gb_Donkey_Kong",
        "name": "Donkey Kong",
        "system": "gb",
        "rom_path": "roms/gbc/Donkey Kong (World) (Rev A) (SGB Enhanced).gb",
        "core": "gambatte",
        "image": "assets/gb/Donkey Kong.png"
    },
    {
        "id": "gbc_Legend_of_Zelda,_The_-_Link's_Awakening_DX",
        "name": "Legend of Zelda, The - Link's Awakening DX",
        "system": "gbc",
        "rom_path": "roms/gbc/Legend of Zelda, The - Link's Awakening DX (USA, Europe) (Rev 2) (SGB Enhanced) (GB Compatible).gbc",
        "core": "gambatte",
        "image": "assets/gbc/Legend of Zelda The - Links Awakening DX.png"
    },
    {
        "id": "gb_Metroid_II_-_EJRTQ_Colorization_-_Canon_Samus",
        "name": "Metroid II - EJRTQ Colorization - Canon Samus",
        "system": "gb",
        "rom_path": "roms/gbc/Metroid II - EJRTQ Colorization (v1.3) - Canon Samus.gb",
        "core": "gambatte",
        "image": "assets/gb/Metroid II - EJRTQ Colorization - Canon Samus.png"
    },
    {
        "id": "gbc_Pokemon_Blue_-_Color_Gen2",
        "name": "Pokemon Blue - Color Gen2",
        "system": "gbc",
        "rom_path": "roms/gbc/Pokemon Blue - Color Gen2 (v1.2).gbc",
        "core": "gambatte",
        "image": "assets/gbc/Pokemon Blue - Color Gen2.png"
    },
    {
        "id": "gbc_Pokemon_Blue",
        "name": "Pokemon Blue",
        "system": "gbc",
        "rom_path": "roms/gbc/Pokemon Blue.gbc",
        "core": "gambatte",
        "image": "assets/gbc/Pokemon Blue.png"
    },
    {
        "id": "gbc_Pokemon_Pinball_Generations_v1.5",
        "name": "Pokemon Pinball Generations v1.5",
        "system": "gbc",
        "rom_path": "roms/gbc/Pokemon Pinball Generations v1.5.gbc",
        "core": "gambatte",
        "image": "assets/gbc/Pokemon Pinball Generations v1.5.png"
    },
    {
        "id": "gbc_Pokemon_Trading_Card_Game",
        "name": "Pokemon Trading Card Game",
        "system": "gbc",
        "rom_path": "roms/gbc/Pokemon Trading Card Game (USA, Australia).gbc",
        "core": "gambatte",
        "image": "assets/gbc/Pokemon Trading Card Game.png"
    },
    {
        "id": "gbc_Shantae",
        "name": "Shantae",
        "system": "gbc",
        "rom_path": "roms/gbc/Shantae (USA).gbc",
        "core": "gambatte",
        "image": "assets/gbc/Shantae.png"
    },
    {
        "id": "gbc_Super_Mario_Land_2_DX",
        "name": "Super Mario Land 2 DX",
        "system": "gbc",
        "rom_path": "roms/gbc/Super Mario Land 2 DX.gbc",
        "core": "gambatte",
        "image": "assets/gbc/Super Mario Land 2 DX.png"
    },
    {
        "id": "gbc_Survival_Kids",
        "name": "Survival Kids",
        "system": "gbc",
        "rom_path": "roms/gbc/Survival Kids (USA) (SGB Enhanced) (GB Compatible).gbc",
        "core": "gambatte",
        "image": "assets/gbc/Survival Kids.png"
    },
    {
        "id": "gbc_Tetris_DX",
        "name": "Tetris DX",
        "system": "gbc",
        "rom_path": "roms/gbc/Tetris DX (World) (SGB Enhanced) (GB Compatible).gbc",
        "core": "gambatte",
        "image": "assets/gbc/Tetris DX.png"
    },
    {
        "id": "n64_Legend_of_Zelda,_The_-_Majora's_Mask",
        "name": "Legend of Zelda, The - Majora's Mask",
        "system": "n64",
        "rom_path": "roms/n64/Legend of Zelda, The - Majora's Mask (USA).z64",
        "core": "mupen64plus_next",
        "image": "assets/n64/Legend of Zelda The - Majoras Mask.png"
    },
    {
        "id": "n64_Super_Mario_64",
        "name": "Super Mario 64",
        "system": "n64",
        "rom_path": "roms/n64/Super Mario 64 (U) [!].z64",
        "core": "mupen64plus_next",
        "image": "assets/n64/Super Mario 64.png"
    },
    {
        "id": "neogeo_Metal_Slug_X_-_Super_Vehicle-001",
        "name": "Metal Slug X - Super Vehicle-001",
        "system": "neogeo",
        "rom_path": "roms/neogeo/mslugx.zip",
        "core": "mame2003_plus",
        "image": "assets/neogeo/Metal Slug X - Super Vehicle-001.png"
    },
    {
        "id": "neogeo_Neo_Geo_BIOS",
        "name": "Neo Geo BIOS",
        "system": "neogeo",
        "rom_path": "roms/neogeo/neogeo.zip",
        "core": "mame2003_plus",
        "image": "assets/default.png"
    },
    {
        "id": "nes_Contra",
        "name": "Contra",
        "system": "nes",
        "rom_path": "roms/nes/Contra (USA).nes",
        "core": "fceumm",
        "image": "assets/nes/Contra.png"
    },
    {
        "id": "nes_Donkey_Kong",
        "name": "Donkey Kong",
        "system": "nes",
        "rom_path": "roms/nes/Donkey Kong (World) (Rev 1).nes",
        "core": "fceumm",
        "image": "assets/nes/Donkey Kong.png"
    },
    {
        "id": "nes_Kirby's_Adventure",
        "name": "Kirby's Adventure",
        "system": "nes",
        "rom_path": "roms/nes/Kirby's Adventure (USA) (Rev 1).nes",
        "core": "fceumm",
        "image": "assets/nes/Kirbys Adventure.png"
    },
    {
        "id": "nes_Legend_of_Zelda,_The",
        "name": "Legend of Zelda, The",
        "system": "nes",
        "rom_path": "roms/nes/Legend of Zelda, The (USA) (Rev 1).nes",
        "core": "fceumm",
        "image": "assets/nes/Legend of Zelda The.png"
    },
    {
        "id": "nes_Mega_Man_6",
        "name": "Mega Man 6",
        "system": "nes",
        "rom_path": "roms/nes/Mega Man 6 (USA).nes",
        "core": "fceumm",
        "image": "assets/nes/Mega Man 6.png"
    },
    {
        "id": "nes_Super_Mario_Bros.",
        "name": "Super Mario Bros.",
        "system": "nes",
        "rom_path": "roms/nes/Super Mario Bros. (World).nes",
        "core": "fceumm",
        "image": "assets/nes/Super Mario Bros..png"
    },
    {
        "id": "nes_Super_Mario_Bros._2",
        "name": "Super Mario Bros. 2",
        "system": "nes",
        "rom_path": "roms/nes/Super Mario Bros. 2 (USA) (Rev 1).nes",
        "core": "fceumm",
        "image": "assets/nes/Super Mario Bros. 2.png"
    },
    {
        "id": "nes_Super_Mario_Bros._3",
        "name": "Super Mario Bros. 3",
        "system": "nes",
        "rom_path": "roms/nes/Super Mario Bros. 3 (USA) (Rev 1).nes",
        "core": "fceumm",
        "image": "assets/nes/Super Mario Bros. 3.png"
    },
    {
        "id": "nes_Teenage_Mutant_Ninja_Turtles_II_-_The_Arcade_Game",
        "name": "Teenage Mutant Ninja Turtles II - The Arcade Game",
        "system": "nes",
        "rom_path": "roms/nes/Teenage Mutant Ninja Turtles II - The Arcade Game (USA).nes",
        "core": "fceumm",
        "image": "assets/nes/Teenage Mutant Ninja Turtles II - The Arcade Game.png"
    },
    {
        "id": "nes_Teenage_Mutant_Ninja_Turtles_III_-_The_Manhattan_Project",
        "name": "Teenage Mutant Ninja Turtles III - The Manhattan Project",
        "system": "nes",
        "rom_path": "roms/nes/Teenage Mutant Ninja Turtles III - The Manhattan Project (USA).nes",
        "core": "fceumm",
        "image": "assets/nes/Teenage Mutant Ninja Turtles III - The Manhattan Project.png"
    },
    {
        "id": "ngp_Bust-A-Move_Pocket",
        "name": "Bust-A-Move Pocket",
        "system": "ngp",
        "rom_path": "roms/ngp/Bust-A-Move Pocket (UE).npc",
        "core": "mednafen_ngp",
        "image": "assets/ngp/Bust-A-Move Pocket.png"
    },
    {
        "id": "ngp_Last_Blade,_The",
        "name": "Last Blade, The",
        "system": "ngp",
        "rom_path": "roms/ngp/Last Blade, The (UE) [!].npc",
        "core": "mednafen_ngp",
        "image": "assets/ngp/Last Blade The.png"
    },
    {
        "id": "ngp_Metal_Slug_-_1st_Mission",
        "name": "Metal Slug - 1st Mission",
        "system": "ngp",
        "rom_path": "roms/ngp/Metal Slug - 1st Mission (JUE).npc",
        "core": "mednafen_ngp",
        "image": "assets/ngp/Metal Slug - 1st Mission.png"
    },
    {
        "id": "ngp_Metal_Slug_-_2nd_Mission",
        "name": "Metal Slug - 2nd Mission",
        "system": "ngp",
        "rom_path": "roms/ngp/Metal Slug - 2nd Mission (JUE) [!].npc",
        "core": "mednafen_ngp",
        "image": "assets/ngp/Metal Slug - 2nd Mission.png"
    },
    {
        "id": "ngp_Neo_Turf_Masters",
        "name": "Neo Turf Masters",
        "system": "ngp",
        "rom_path": "roms/ngp/Neo Turf Masters (JUE) [!].npc",
        "core": "mednafen_ngp",
        "image": "assets/ngp/Neo Turf Masters.png"
    },
    {
        "id": "ngp_Pocket_Tennis_Color",
        "name": "Pocket Tennis Color",
        "system": "ngp",
        "rom_path": "roms/ngp/Pocket Tennis Color (JUE) [!].npc",
        "core": "mednafen_ngp",
        "image": "assets/ngp/Pocket Tennis Color.png"
    },
    {
        "id": "ngp_Puyo_Pop",
        "name": "Puyo Pop",
        "system": "ngp",
        "rom_path": "roms/ngp/Puyo Pop (World) (En,Ja) (v1.06).ngc",
        "core": "mednafen_ngp",
        "image": "assets/ngp/Puyo Pop.png"
    },
    {
        "id": "ngp_Rockman_-_Battle_&_Fighters",
        "name": "Rockman - Battle & Fighters",
        "system": "ngp",
        "rom_path": "roms/ngp/Rockman - Battle & Fighters (English v1.0).ngc",
        "core": "mednafen_ngp",
        "image": "assets/ngp/Rockman - Battle  Fighters.png"
    },
    {
        "id": "ngp_SNK_Vs_Capcom_-_Match_Of_The_Millennium",
        "name": "SNK Vs Capcom - Match Of The Millennium",
        "system": "ngp",
        "rom_path": "roms/ngp/SNK Vs Capcom - Match Of The Millennium (JUE) [!].npc",
        "core": "mednafen_ngp",
        "image": "assets/ngp/SNK Vs Capcom - Match Of The Millennium.png"
    },
    {
        "id": "ngp_SNK_vs._Capcom_-_Card_Fighters'_Clash_-_SNK_Version",
        "name": "SNK vs. Capcom - Card Fighters' Clash - SNK Version",
        "system": "ngp",
        "rom_path": "roms/ngp/SNK vs. Capcom - Card Fighters' Clash - SNK Version (USA).ngc",
        "core": "mednafen_ngp",
        "image": "assets/ngp/SNK vs. Capcom - Card Fighters Clash - SNK Version.png"
    },
    {
        "id": "segaMD_Aladdin",
        "name": "Aladdin",
        "system": "segaMD",
        "rom_path": "roms/sega_md/Aladdin (USA).md",
        "core": "segaMD",
        "image": "assets/segaMD/Aladdin.png"
    },
    {
        "id": "segaMD_Castlevania_-_Bloodlines",
        "name": "Castlevania - Bloodlines",
        "system": "segaMD",
        "rom_path": "roms/sega_md/Castlevania - Bloodlines (USA).md",
        "core": "segaMD",
        "image": "assets/segaMD/Castlevania - Bloodlines.png"
    },
    {
        "id": "segaMD_Earthworm_Jim_2",
        "name": "Earthworm Jim 2",
        "system": "segaMD",
        "rom_path": "roms/sega_md/Earthworm Jim 2 (USA).md",
        "core": "segaMD",
        "image": "assets/segaMD/Earthworm Jim 2.png"
    },
    {
        "id": "segaMD_Gunstar_Heroes",
        "name": "Gunstar Heroes",
        "system": "segaMD",
        "rom_path": "roms/sega_md/Gunstar Heroes (USA).md",
        "core": "segaMD",
        "image": "assets/segaMD/Gunstar Heroes.png"
    },
    {
        "id": "segaMD_NBA_Jam_-_Tournament_Edition",
        "name": "NBA Jam - Tournament Edition",
        "system": "segaMD",
        "rom_path": "roms/sega_md/NBA Jam - Tournament Edition (World).md",
        "core": "segaMD",
        "image": "assets/segaMD/NBA Jam - Tournament Edition.png"
    },
    {
        "id": "segaMD_Phantasy_Star_IV",
        "name": "Phantasy Star IV",
        "system": "segaMD",
        "rom_path": "roms/sega_md/Phantasy Star IV (USA).md",
        "core": "segaMD",
        "image": "assets/segaMD/Phantasy Star IV.png"
    },
    {
        "id": "segaMD_Sonic_&_Knuckles_+_Sonic_The_Hedgehog_3",
        "name": "Sonic & Knuckles + Sonic The Hedgehog 3",
        "system": "segaMD",
        "rom_path": "roms/sega_md/Sonic & Knuckles + Sonic The Hedgehog 3 (USA).md",
        "core": "segaMD",
        "image": "https://raw.githubusercontent.com/libretro-thumbnails/Sega_-_Mega_Drive_-_Genesis/master/Named_Boxarts/Sonic%20The%20Hedgehog%203%20%28USA%29.png"
    },
    {
        "id": "segaMD_Teenage_Mutant_Ninja_Turtles_-_The_Hyperstone_Heist",
        "name": "Teenage Mutant Ninja Turtles - The Hyperstone Heist",
        "system": "segaMD",
        "rom_path": "roms/sega_md/Teenage Mutant Ninja Turtles - The Hyperstone Heist (USA).md",
        "core": "segaMD",
        "image": "assets/segaMD/Teenage Mutant Ninja Turtles - The Hyperstone Heist.png"
    },
    {
        "id": "segaMD_ToeJam_&_Earl",
        "name": "ToeJam & Earl",
        "system": "segaMD",
        "rom_path": "roms/sega_md/ToeJam & Earl (USA, Europe, Korea).md",
        "core": "segaMD",
        "image": "assets/segaMD/ToeJam  Earl.png"
    },
    {
        "id": "segaMD_Ultimate_Mortal_Kombat_3",
        "name": "Ultimate Mortal Kombat 3",
        "system": "segaMD",
        "rom_path": "roms/sega_md/Ultimate Mortal Kombat 3 (USA).md",
        "core": "segaMD",
        "image": "assets/segaMD/Ultimate Mortal Kombat 3.png"
    },
    {
        "id": "snes_Contra_III_-_The_Alien_Wars",
        "name": "Contra III - The Alien Wars",
        "system": "snes",
        "rom_path": "roms/snes/Contra III - The Alien Wars (USA).sfc",
        "core": "snes9x",
        "image": "assets/snes/Contra III - The Alien Wars.png"
    },
    {
        "id": "snes_Donkey_Kong_Country_2_-_Diddy's_Kong_Quest",
        "name": "Donkey Kong Country 2 - Diddy's Kong Quest",
        "system": "snes",
        "rom_path": "roms/snes/Donkey Kong Country 2 - Diddy's Kong Quest (USA) (En,Fr) (Rev 1).sfc",
        "core": "snes9x",
        "image": "assets/snes/Donkey Kong Country 2 - Diddys Kong Quest.png"
    },
    {
        "id": "snes_Mega_Man_X3",
        "name": "Mega Man X3",
        "system": "snes",
        "rom_path": "roms/snes/Mega Man X3 (USA).sfc",
        "core": "snes9x",
        "image": "assets/snes/Mega Man X3.png"
    },
    {
        "id": "snes_Street_Fighter_II_Turbo",
        "name": "Street Fighter II Turbo",
        "system": "snes",
        "rom_path": "roms/snes/Street Fighter II Turbo (USA) (Rev 1).sfc",
        "core": "snes9x",
        "image": "assets/snes/Street Fighter II Turbo.png"
    },
    {
        "id": "snes_Super_Bomberman_2",
        "name": "Super Bomberman 2",
        "system": "snes",
        "rom_path": "roms/snes/Super Bomberman 2 (USA).sfc",
        "core": "snes9x",
        "image": "assets/snes/Super Bomberman 2.png"
    },
    {
        "id": "snes_Super_Castlevania_IV",
        "name": "Super Castlevania IV",
        "system": "snes",
        "rom_path": "roms/snes/Super Castlevania IV (USA).sfc",
        "core": "snes9x",
        "image": "assets/snes/Super Castlevania IV.png"
    },
    {
        "id": "snes_Super_Mario_World",
        "name": "Super Mario World",
        "system": "snes",
        "rom_path": "roms/snes/Super Mario World (USA).sfc",
        "core": "snes9x",
        "image": "assets/snes/Super Mario World.png"
    },
    {
        "id": "snes_Super_Punch-Out!!",
        "name": "Super Punch-Out!!",
        "system": "snes",
        "rom_path": "roms/snes/Super Punch-Out!! (USA).sfc",
        "core": "snes9x",
        "image": "assets/snes/Super Punch-Out.png"
    },
    {
        "id": "snes_Teenage_Mutant_Ninja_Turtles_IV_-_Turtles_in_Time",
        "name": "Teenage Mutant Ninja Turtles IV - Turtles in Time",
        "system": "snes",
        "rom_path": "roms/snes/Teenage Mutant Ninja Turtles IV - Turtles in Time (USA).sfc",
        "core": "snes9x",
        "image": "assets/snes/Teenage Mutant Ninja Turtles IV - Turtles in Time.png"
    },
    {
        "id": "snes_The_Legend_of_Zelda_-_A_Link_to_the_Past",
        "name": "The Legend of Zelda - A Link to the Past",
        "system": "snes",
        "rom_path": "roms/snes/The Legend of Zelda - A Link to the Past (USA).sfc",
        "core": "snes9x",
        "image": "assets/snes/The Legend of Zelda - A Link to the Past.png"
    }
]